genzql/__init__.py
genzql/cleaner.py
genzql/grammar.py
genzql/loader.py
genzql/main.py
genzql/parser.py
genzql/renderer.py
genzql/translator.py
genzql/types.py
genzql/zql_grammar.tmjd
genzql-0.3.0.dist-info/LICENSE
genzql-0.3.0.dist-info/METADATA
genzql-0.3.0.dist-info/WHEEL
genzql-0.3.0.dist-info/RECORD
